yt_astro_analysis/__init__.py
yt_astro_analysis/cosmological_observation/__init__.py
yt_astro_analysis/cosmological_observation/api.py
yt_astro_analysis/cosmological_observation/cosmology_splice.py
yt_astro_analysis/cosmological_observation/light_cone/__init__.py
yt_astro_analysis/cosmological_observation/light_cone/api.py
yt_astro_analysis/cosmological_observation/light_cone/light_cone.py
yt_astro_analysis/cosmological_observation/light_cone/light_cone_projection.py
yt_astro_analysis/cosmological_observation/light_cone/tests/__init__.py
yt_astro_analysis/cosmological_observation/light_cone/tests/test_light_cone.py
yt_astro_analysis/halo_analysis/__init__.py
yt_astro_analysis/halo_analysis/api.py
yt_astro_analysis/halo_analysis/halo_catalog/__init__.py
yt_astro_analysis/halo_analysis/halo_catalog/analysis_operators.py
yt_astro_analysis/halo_analysis/halo_catalog/analysis_pipeline.py
yt_astro_analysis/halo_analysis/halo_catalog/halo_callbacks.py
yt_astro_analysis/halo_analysis/halo_catalog/halo_catalog.py
yt_astro_analysis/halo_analysis/halo_catalog/halo_filters.py
yt_astro_analysis/halo_analysis/halo_catalog/halo_finding_methods.py
yt_astro_analysis/halo_analysis/halo_catalog/halo_object.py
yt_astro_analysis/halo_analysis/halo_catalog/halo_quantities.py
yt_astro_analysis/halo_analysis/halo_catalog/halo_recipes.py
yt_astro_analysis/halo_analysis/halo_catalog/plot_modifications.py
yt_astro_analysis/halo_analysis/halo_finding/__init__.py
yt_astro_analysis/halo_analysis/halo_finding/api.py
yt_astro_analysis/halo_analysis/halo_finding/halo_objects.py
yt_astro_analysis/halo_analysis/halo_finding/fof/EnzoFOF.c
yt_astro_analysis/halo_analysis/halo_finding/fof/EnzoFOF.cpython-312-x86_64-linux-musl.so
yt_astro_analysis/halo_analysis/halo_finding/fof/README
yt_astro_analysis/halo_analysis/halo_finding/fof/__init__.py
yt_astro_analysis/halo_analysis/halo_finding/fof/kd.c
yt_astro_analysis/halo_analysis/halo_finding/fof/kd.h
yt_astro_analysis-1.1.4.dist-info/METADATA
yt_astro_analysis-1.1.4.dist-info/WHEEL
yt_astro_analysis-1.1.4.dist-info/top_level.txt
yt_astro_analysis-1.1.4.dist-info/RECORD
yt_astro_analysis-1.1.4.dist-info/licenses/COPYING.txt
