Metadata-Version: 2.4
Name: yt_astro_analysis
Version: 1.1.4
Summary: yt astrophysical analysis modules extension
Author-email: The yt project <yt-dev@python.org>
License: BSD 3-Clause
Project-URL: Homepage, https://yt-project.org/
Project-URL: Documentation, https://yt-astro-analysis.readthedocs.io/
Project-URL: Source, https://github.com/yt-project/yt_astro_analysis/
Project-URL: Tracker, https://github.com/yt-project/yt_astro_analysis/issues
Keywords: astronomy astrophysics visualization amr adaptivemeshrefinement
Classifier: Development Status :: 5 - Production/Stable
Classifier: Environment :: Console
Classifier: Intended Audience :: Science/Research
Classifier: License :: OSI Approved :: BSD License
Classifier: Natural Language :: English
Classifier: Operating System :: MacOS :: MacOS X
Classifier: Operating System :: POSIX :: Linux
Classifier: Operating System :: Unix
Classifier: Programming Language :: C
Classifier: Programming Language :: Python :: 3
Classifier: Programming Language :: Python :: 3 :: Only
Classifier: Programming Language :: Python :: 3.9
Classifier: Programming Language :: Python :: 3.10
Classifier: Programming Language :: Python :: 3.11
Classifier: Programming Language :: Python :: 3.12
Classifier: Topic :: Scientific/Engineering :: Astronomy
Classifier: Topic :: Scientific/Engineering :: Physics
Classifier: Topic :: Scientific/Engineering :: Visualization
Requires-Python: >=3.9
License-File: COPYING.txt
Requires-Dist: h5py>=3.1.0
Requires-Dist: yt>=4.0.1
Requires-Dist: numpy<3,>=1.19.3
Requires-Dist: packaging>=20.9
Dynamic: license-file
